unicity/__init__.py
unicity/mrtns.py
unicity/winnowing.py
unicity-0.5.dist-info/LICENSE
unicity-0.5.dist-info/METADATA
unicity-0.5.dist-info/WHEEL
unicity-0.5.dist-info/top_level.txt
unicity-0.5.dist-info/RECORD
