Metadata-Version: 2.1
Name: unicity
Version: 0.5
Summary: Batch testing and similarity checking of python code.
Home-page: https://github.com/ddempsey/unicity
Author: David Dempsey
Author-email: ddempsey786@gmail.com
License: UNKNOWN
Platform: UNKNOWN
Classifier: Programming Language :: Python :: 3
Classifier: License :: OSI Approved :: MIT License
Classifier: Operating System :: OS Independent
Requires-Dist: numpy
Requires-Dist: scipy
Requires-Dist: matplotlib
Requires-Dist: fuzzywuzzy
